{
  "modeldefs": [
    "ModelDef1",
    "ModelDef2",
    "ModelDef3"
  ],
  "indexedModels": [
    {
      "id": "ModelDef1",
      "fields": [
        {
          "id": "1",
          "name": "Model11",
          "indexedField": 18
        },
        {
          "id": "2",
          "name": "Model12",
          "indexedField": 19
        },
        {
          "id": "3",
          "name": "Model13",
          "indexedField": 20
        }
      ]
    },
    {
      "id": "ModelDef2",
      "fields": [
        {
          "id": "1",
          "name": "Model21",
          "indexedField": 18
        },
        {
          "id": "2",
          "name": "Model22",
          "indexedField": 19
        },
        {
          "id": "3",
          "name": "Model23",
          "indexedField": 20
        }
      ]
    },
    {
      "id": "ModelDef3",
      "fields": [
        {
          "id": "1",
          "name": "Model31",
          "indexedField": 18
        },
        {
          "id": "2",
          "name": "Model32",
          "indexedField": 19
        },
        {
          "id": "3",
          "name": "Model33",
          "indexedField": 20
        }
      ]
    }
  ],
  "models": [
    {
      "id": "ModelDef1_1",
      "fields": {
        "id": "1",
        "name": "Model1",
        "indexedField": {
          "type": "java.lang.Integer",
          "value": 18
        },
        "field1": {
          "type": "java.lang.Class",
          "value": "ModelDef1"
        }
      }
    },
    {
      "id": "ModelDef1_2",
      "fields": {
        "id": "2",
        "name": "Model2",
        "indexedField": {
          "type": "java.lang.Integer",
          "value": 19
        },
        "field1": {
          "type": "java.lang.Boolean",
          "value": false
        }
      }
    },
    {
      "id": "ModelDef1_3",
      "fields": {
        "id": "3",
        "name": "Model3",
        "indexedField": {
          "type": "java.lang.Integer",
          "value": 20
        },
        "field1": {
          "type": "java.lang.Class",
          "value": "ModelDef1"
        }
      }
    },
    {
      "id": "ModelDef2_1",
      "fields": {
        "id": "1",
        "name": "Model1",
        "indexedField": {
          "type": "java.lang.Integer",
          "value": 18
        },
        "field1": "string"
      }
    },
    {
      "id": "ModelDef2_2",
      "fields": {
        "id": "2",
        "name": "Model2",
        "indexedField": {
          "type": "java.lang.Integer",
          "value": 19
        },
        "field1": 1
      }
    },
    {
      "id": "ModelDef2_3",
      "fields": {
        "id": "3",
        "name": "Model3",
        "indexedField": {
          "type": "java.lang.Integer",
          "value": 20
        },
        "field1": false
      }
    },
    {
      "id": "ModelDef3_1",
      "fields": {
        "id": "1",
        "name": "Model1",
        "indexedField": {
          "type": "java.lang.Integer",
          "value": 18
        },
        "field1": "string"
      }
    },
    {
      "id": "ModelDef3_2",
      "fields": {
        "id": "2",
        "name": "Model2",
        "indexedField": {
          "type": "java.lang.Integer",
          "value": 19
        },
        "field1": 1
      }
    },
    {
      "id": "ModelDef3_3",
      "fields": {
        "id": "3",
        "name": "Model3",
        "indexedField": {
          "type": "java.lang.Integer",
          "value": 29
        },
        "field1": false
      }
    }
  ]
}